{"data": {"id": 10935, "name": "Cryptocurrencies.ai", "symbol": "CCAI", "slug": "cryptocurrencies-ai", "category": "token", "description": "Cryptocurrencies.ai is an advanced platform for crypto-traders. Our goal is provide to our users tools to reduce your pain, improve your UX and give the opportunity to resolve all your needs related to trading crypto within one platform.\r\nOn the platform you can do convenient things with human-based interface that aren\u2019t available on the crypto exchanges today, but are so necessary for traders:\r\n\r\nFirst of all you can create native account on our platform and be sure that your funds keep safe on our top-exchange partner.\r\nTrade multiple accounts on one terminal and use Smart Orders to set both stop loss and take a profit and other advanced settings with few clicks.\r\n\r\nClassic terminal\r\nSmart order is an algorithm to make your manual trading easy and safe:\r\nset both stop loss and take a profit at one order with advanced settings like trailing, timeout or split profit targets.\r\nLong & Short same asset or create separate long and short portfolios to manage your risk.\r\n\r\nSmart order settings\r\nUse trailing entry or trailing profit to follow the price until get most profitable price to open or close your position.\r\nTrack your trading results, analyze your history with our advanced transactions page.\r\nSee your profit & loss for all portfolios, any account, any asset and even an individual trade!\r\nRebalance your portfolio to distribute assets in a few clicks.\r\n\r\nCreate FuturesWars competition and earn with our referral program or just join existing competitions and win!\r\n\r\nConnect your own bot to our API with opensource Python library and focus on your strategy, not on engineering. Improve your algorithm together with our smart trading features.", "dateAdded": "2021-07-16T00:00:00.000Z", "status": "active", "notice": "", "latestUpdateTime": "2021-07-31T11:54:43.000Z", "watchCount": "357", "dateLaunched": "2021-06-09T00:00:00.000Z", "tags": [], "urls": {"website": ["https://cryptocurrencies.ai/"], "technical_doc": [], "explorer": ["https://solscan.io/token/E5ndSkaB17Dm7CsD22dvcjfrYSDLCxFcMd6z8ddCk5wp"], "source_code": [], "message_board": ["https://ccaiofficial.medium.com/"], "chat": ["https://t.me/CCAI_Official", "https://discord.com/invite/2EaKvrs"], "announcement": ["https://t.me/CCAI_Official_ANN"], "reddit": [], "twitter": ["https://twitter.com/CCAI_Official"]}, "volume": 0.0, "volumeChangePercentage24h": 0.0, "statistics": {"price": 1.03226251256874, "priceChangePercentage1h": 0.00619449, "priceChangePercentage24h": -3.26507768, "priceChangePercentage7d": -3.97115207, "priceChangePercentage30d": 0.0, "priceChangePercentage60d": 0.0, "priceChangePercentage90d": 0.0, "marketCap": 0.0, "marketCapChangePercentage24h": 0.0, "fullyDilutedMarketCap": 51613125.63, "fullyDilutedMarketCapChangePercentage24h": 0.0, "circulatingSupply": 0.0, "totalSupply": 0.0, "maxSupply": 50000000.0, "marketCapDominance": 0.0, "rank": 5872, "low24h": 0.9599417, "high24h": 1.07142971, "low7d": 0.9599417, "high7d": 1.16567322, "low30d": 0.84840544, "high30d": 1.16567322, "low90d": 0.84840544, "high90d": 1.16567322, "low52w": 0.84840544, "high52w": 1.16567322, "lowAllTime": 0.84840544, "highAllTime": 1.16567322, "lowAllTimeChangePercentage": 21.67, "highAllTimeChangePercentage": -11.44, "lowAllTimeTimestamp": "2021-07-17T03:28:27.000Z", "highAllTimeTimestamp": "2021-07-26T22:52:07.000Z", "lowYesterday": 1.06357069, "highYesterday": 1.09351297, "openYesterday": 1.07633406, "closeYesterday": 1.06393986, "priceChangePercentageYesterday": -1.15, "volumeYesterday": 0, "ytdPriceChangePercentage": 0.0}, "relatedCoins": [{"id": 1376, "name": "Neo", "slug": "neo", "price": 46.15277603529009, "priceChangePercentage24h": 35.97491332, "priceChangePercentage7d": 52.15383074}, {"id": 6636, "name": "Polkadot", "slug": "polkadot-new", "price": 16.34964051346751, "priceChangePercentage24h": 11.48864478, "priceChangePercentage7d": 20.65721962}, {"id": 109, "name": "DigiByte", "slug": "digibyte", "price": 0.04606059556592, "priceChangePercentage24h": 8.60454635, "priceChangePercentage7d": 18.52026324}, {"id": 1817, "name": "Voyager Token", "slug": "voyager-token", "price": 2.35073162374456, "priceChangePercentage24h": 17.29500189, "priceChangePercentage7d": 25.00533147}, {"id": 3077, "name": "VeChain", "slug": "vechain", "price": 0.08805508567185, "priceChangePercentage24h": 8.49406181, "priceChangePercentage7d": 22.66853882}, {"id": 1567, "name": "Nano", "slug": "nano", "price": 4.33953608915345, "priceChangePercentage24h": 5.35932698, "priceChangePercentage7d": 10.52614735}, {"id": 7226, "name": "Injective Protocol", "slug": "injective-protocol", "price": 6.81208358366918, "priceChangePercentage24h": 11.33740637, "priceChangePercentage7d": 18.63805644}, {"id": 2062, "name": "Aion", "slug": "aion", "price": 0.12884983830176, "priceChangePercentage24h": 6.8379087, "priceChangePercentage7d": 12.06023177}, {"id": 3890, "name": "Polygon", "slug": "polygon", "price": 1.05089512675303, "priceChangePercentage24h": 4.36180993, "priceChangePercentage7d": 14.01964127}], "relatedExchanges": [], "isAudited": false, "holders": {}}, "status": {"timestamp": "2021-07-31T11:55:58.654Z", "error_code": "0", "error_message": "SUCCESS", "elapsed": "7", "credit_count": 0}}