{"data": {"id": 2900, "name": "Project Pai", "symbol": "PAI", "slug": "project-pai", "category": "coin", "description": "Project Pai (PAI) is a cryptocurrency . Project Pai has a current supply of 1,764,389,690 with 1,561,298,888.9700427 in circulation. The last known price of Project Pai is 0.01410569 USD and is down -6.64 over the last 24 hours. It is currently trading on 9 active market(s) with $989,348.39 traded over the last 24 hours. More information can be found at https://projectpai.com/.", "dateAdded": "2018-07-05T00:00:00.000Z", "status": "active", "notice": "", "latestUpdateTime": "2021-07-31T08:47:28.000Z", "watchCount": "4529", "launchPrice": 1.30822, "tags": [{"slug": "services", "name": "Services", "category": "PROPERTY"}, {"slug": "ai-big-data", "name": "AI & Big Data", "category": "PROPERTY"}, {"slug": "identity", "name": "Identity", "category": "PROPERTY"}], "urls": {"website": ["https://projectpai.com/"], "technical_doc": [], "explorer": ["https://paichain.info/"], "source_code": ["https://www.github.com/projectpai/"], "message_board": ["https://medium.com/project-pai", "https://www.paiforum.com/"], "chat": ["https://t.me/projectpai", "https://discord.gg/YP74pnw"], "announcement": [], "reddit": ["https://reddit.com/r/ProjectPai"], "twitter": ["https://twitter.com/ProjectPai"]}, "volume": 964861.86724377, "volumeChangePercentage24h": -57.8478, "statistics": {"price": 0.01407210759547, "priceChangePercentage1h": -0.264812, "priceChangePercentage24h": -2.98412766, "priceChangePercentage7d": 15.87847384, "priceChangePercentage30d": -7.60026357, "priceChangePercentage60d": -36.81273485, "priceChangePercentage90d": -74.95046288, "marketCap": 21970765.95, "marketCapChangePercentage24h": -2.9729, "fullyDilutedMarketCap": 24828681.56, "fullyDilutedMarketCapChangePercentage24h": 8.88, "circulatingSupply": 1561298888.9700427, "totalSupply": 1764389690.0, "marketCapDominance": 0.0014, "rank": 628, "roi": -98.92433172, "low24h": 0.01370341, "high24h": 0.0154558, "low7d": 0.01169783, "high7d": 0.01650823, "low30d": 0.01026563, "high30d": 0.01917942, "low90d": 0.01023776, "high90d": 0.07091183, "low52w": 0.0045789, "high52w": 0.14732018, "lowAllTime": 0.0045789, "highAllTime": 1.53557003, "lowAllTimeChangePercentage": 207.33, "highAllTimeChangePercentage": -99.08, "lowAllTimeTimestamp": "2021-06-14T09:43:22.000Z", "highAllTimeTimestamp": "2018-07-09T07:54:22.000Z", "lowYesterday": 0.01370341, "highYesterday": 0.01843827, "openYesterday": 0.01463334, "closeYesterday": 0.01441385, "priceChangePercentageYesterday": -1.5, "volumeYesterday": 2293165.15, "turnover": 0.04391571, "ytdPriceChangePercentage": 132.8979}, "relatedCoins": [{"id": 7758, "name": "Eauric", "slug": "eauric", "price": 0.17127937780763, "priceChangePercentage24h": 0.3964388, "priceChangePercentage7d": -42.80338932}, {"id": 7576, "name": "HARD Protocol", "slug": "hard-protocol", "price": 0.73659885158055, "priceChangePercentage24h": 5.52834872, "priceChangePercentage7d": 13.85548796}, {"id": 7838, "name": "Base Protocol", "slug": "base-protocol", "price": 1.58287963833012, "priceChangePercentage24h": -3.05617548, "priceChangePercentage7d": -44.55975252}, {"id": 8120, "name": "Whiteheart", "slug": "whiteheart", "price": 857.6499485288488, "priceChangePercentage24h": 9.4219495, "priceChangePercentage7d": 17.09750856}, {"id": 7760, "name": "Komet", "slug": "komet", "price": 33.0827121194465, "priceChangePercentage24h": 3.93322715, "priceChangePercentage7d": 16.13797157}, {"id": 7571, "name": "Social Rocket", "slug": "social-rocket", "price": 0.23524585019506, "priceChangePercentage24h": 3.93322715, "priceChangePercentage7d": 9.88993321}, {"id": 1886, "name": "Dent", "slug": "dent", "price": 0.00252958619406, "priceChangePercentage24h": 6.65415619, "priceChangePercentage7d": 17.33680981}, {"id": 7440, "name": "BarnBridge", "slug": "barnbridge", "price": 21.39265045719082, "priceChangePercentage24h": 2.87862593, "priceChangePercentage7d": -4.59435099}, {"id": 5444, "name": "Cartesi", "slug": "cartesi", "price": 0.41558858946707, "priceChangePercentage24h": 4.61840988, "priceChangePercentage7d": 13.94223807}, {"id": 6991, "name": "Sashimi", "slug": "sashimi", "price": 0.02709411630037, "priceChangePercentage24h": 2.92086428, "priceChangePercentage7d": -4.71952453}], "relatedExchanges": [{"id": 102, "name": "Huobi Global", "slug": "huobi-global"}, {"id": 497, "name": "BiONE", "slug": "bione"}, {"id": 333, "name": "LBank", "slug": "lbank"}, {"id": 463, "name": "Huobi Korea", "slug": "huobi-korea"}, {"id": 760, "name": "Huobi Indonesia", "slug": "huobi-indonesia"}], "isAudited": false, "holders": {}}, "status": {"timestamp": "2021-07-31T08:48:58.263Z", "error_code": "0", "error_message": "SUCCESS", "elapsed": "6", "credit_count": 0}}