{"data": {"id": 3233, "name": "Ulord", "symbol": "UT", "slug": "ulord", "category": "coin", "description": "Ulord (UT) is a cryptocurrency . Ulord has a current supply of 177,939,938.762 with 80,442,293.35883602 in circulation. The last known price of Ulord is 0.02539572 USD and is down -0.75 over the last 24 hours. It is currently trading on 1 active market(s) with $0.00 traded over the last 24 hours. More information can be found at https://ulord.one.", "dateAdded": "2018-09-06T00:00:00.000Z", "status": "active", "notice": "", "latestUpdateTime": "2021-07-31T08:50:05.000Z", "watchCount": "803", "launchPrice": 0.146296, "tags": [], "urls": {"website": ["https://ulord.one"], "technical_doc": [], "explorer": ["https://explorer.ulord.one/"], "source_code": ["https://github.com/UlordChain/UlordChain"], "message_board": [], "chat": [], "announcement": [], "reddit": [], "twitter": ["https://twitter.com/UlordChain"]}, "volume": 0.0, "volumeChangePercentage24h": 0.0, "statistics": {"price": 0.02848771400859, "priceChangePercentage1h": 21.22180116, "priceChangePercentage24h": 23.11240033, "priceChangePercentage7d": 24.68695664, "priceChangePercentage30d": 9.32939076, "priceChangePercentage60d": -9.84311082, "priceChangePercentage90d": -21.10619897, "marketCap": 2291617.05, "marketCapChangePercentage24h": 23.1453, "fullyDilutedMarketCap": 28487714.01, "fullyDilutedMarketCapChangePercentage24h": 7.1, "circulatingSupply": 80442293.35883602, "totalSupply": 177939938.762, "maxSupply": 1000000000.0, "marketCapDominance": 0.0001, "rank": 1389, "roi": -80.52734592, "low24h": 0.01956156, "high24h": 0.03245649, "low7d": 0.01650792, "high7d": 0.03245649, "low30d": 0.01399261, "high30d": 0.03255482, "low90d": 0.01399261, "high90d": 0.06780483, "low52w": 0.00357304, "high52w": 0.06780483, "lowAllTime": 0.00127924, "highAllTime": 0.17756562, "lowAllTimeChangePercentage": 2126.92, "highAllTimeChangePercentage": -83.96, "lowAllTimeTimestamp": "2019-10-03T08:43:09.000Z", "highAllTimeTimestamp": "2018-09-07T06:54:22.000Z", "lowYesterday": 0.01949041, "highYesterday": 0.03245649, "openYesterday": 0.02628576, "closeYesterday": 0.02739236, "priceChangePercentageYesterday": 4.21, "volumeYesterday": 0, "turnover": 0.0, "ytdPriceChangePercentage": 133.4364}, "relatedCoins": [{"id": 2034, "name": "Everex", "slug": "everex", "price": 0.37112780079095, "priceChangePercentage24h": 3.4286502, "priceChangePercentage7d": 16.78855049}, {"id": 3004, "name": "Volt", "slug": "volt", "price": 0.00014940920714, "priceChangePercentage24h": -20.12066453, "priceChangePercentage7d": -1.08438395}, {"id": 6593, "name": "Bitgear", "slug": "bitgear", "price": 0.01082540288674, "priceChangePercentage24h": 6.41869591, "priceChangePercentage7d": 13.94294229}, {"id": 3632, "name": "Opacity", "slug": "opacity", "price": 0.12452669597468, "priceChangePercentage24h": -3.2306137, "priceChangePercentage7d": 62.41293277}, {"id": 7692, "name": "Radix", "slug": "radix", "price": 0.15256612016532, "priceChangePercentage24h": 1.14886505, "priceChangePercentage7d": 11.06515133}, {"id": 6594, "name": "MYX Network", "slug": "myx-network", "price": 0.00106435694417, "priceChangePercentage24h": 22.85508498, "priceChangePercentage7d": 16.02014164}, {"id": 1, "name": "Bitcoin", "slug": "bitcoin", "price": 41756.12969520363, "priceChangePercentage24h": 7.22086788, "priceChangePercentage7d": 24.07692526}, {"id": 5313, "name": "CONTRACOIN", "slug": "contracoin", "price": 0.16062420178574, "priceChangePercentage24h": -1.307707, "priceChangePercentage7d": -5.76749148}, {"id": 1042, "name": "Siacoin", "slug": "siacoin", "price": 0.01407012348841, "priceChangePercentage24h": 6.34864286, "priceChangePercentage7d": 25.43241169}, {"id": 1437, "name": "Zcash", "slug": "zcash", "price": 111.93388289021355, "priceChangePercentage24h": 5.65739007, "priceChangePercentage7d": 13.44587135}], "relatedExchanges": [], "isAudited": false, "holders": {}}, "status": {"timestamp": "2021-07-31T08:51:18.200Z", "error_code": "0", "error_message": "SUCCESS", "elapsed": "8", "credit_count": 0}}