{"data": {"id": 3758, "name": "Max Property Group", "symbol": "MPG", "slug": "max-property-group", "category": "token", "description": "The Max Property Group (MPG) blockchain is a child chain on Ardor and uses the MPG token as a currency to pay for transactions on their crowdfund platform, Max Crowdfund. Transactions include, but are not limited to, listing property, creating an asset, buying/selling investments, and buying and renting out property.\r\nMax Property Group is an international property investment company that is headquartered in Rotterdam, the Netherlands. They also have offices in Germany and the United Kingdom.\r\nIts activities include property management, fund management, buying, selling, renting out of property, and running a property investment academy, Max Property Academy.", "dateAdded": "2019-02-22T00:00:00.000Z", "status": "active", "notice": "", "latestUpdateTime": "2021-07-31T08:54:07.000Z", "watchCount": "771", "dateLaunched": "2019-01-09T00:00:00.000Z", "launchPrice": 0.0546, "tags": [], "urls": {"website": ["https://maxcrowdfund.com"], "technical_doc": [], "explorer": ["https://danb.maxcrowdfund.com/index.html", "https://www.ardor.world/mpg_rich_list/"], "source_code": ["https://bitbucket.org/Jelurida/ardor/src"], "message_board": ["https://medium.com/maxpropertygroup"], "chat": ["https://t.me/MPG_Chat"], "announcement": [], "reddit": [], "twitter": []}, "volume": 1218.60964147, "volumeChangePercentage24h": 8.0425, "statistics": {"price": 0.00960128041758, "priceChangePercentage1h": 0.54630791, "priceChangePercentage24h": 8.04251228, "priceChangePercentage7d": 24.16170379, "priceChangePercentage30d": 24.88787244, "priceChangePercentage60d": 25.17104254, "priceChangePercentage90d": -10.11262401, "marketCap": 1365528.19, "marketCapChangePercentage24h": 8.0425, "fullyDilutedMarketCap": 7535937.95, "fullyDilutedMarketCapChangePercentage24h": 7.86, "circulatingSupply": 142223550.0, "totalSupply": 693372305.0, "maxSupply": 784888850.27, "marketCapDominance": 0.0001, "rank": 1528, "roi": -82.41069528, "low24h": 0.00883139, "high24h": 0.0097024, "low7d": 0.00779282, "high7d": 0.0097024, "low30d": 0.00675332, "high30d": 0.00971418, "low90d": 0.00658035, "high90d": 0.0125795, "low52w": 0.0022856, "high52w": 0.01274604, "lowAllTime": 0.00118952, "highAllTime": 0.04902289, "lowAllTimeChangePercentage": 707.16, "highAllTimeChangePercentage": -80.41, "lowAllTimeTimestamp": "2020-07-07T11:43:22.000Z", "highAllTimeTimestamp": "2019-07-19T17:22:12.000Z", "lowYesterday": 0.00883139, "highYesterday": 0.0096932, "openYesterday": 0.00920194, "closeYesterday": 0.0096897, "priceChangePercentageYesterday": 5.3, "volumeYesterday": 1229.84, "turnover": 0.00089241, "ytdPriceChangePercentage": 59.5573}, "relatedCoins": [{"id": 293, "name": "Bitcoin Plus", "slug": "bitcoin-plus", "price": 9.85923259679152, "priceChangePercentage24h": -29.40220562, "priceChangePercentage7d": -19.69032074}, {"id": 2122, "name": "Ellaism", "slug": "ellaism", "price": 0.00166978789871, "priceChangePercentage24h": 8.04251228, "priceChangePercentage7d": -0.68011385}, {"id": 2120, "name": "Etherparty", "slug": "etherparty", "price": 0.00074230212848, "priceChangePercentage24h": -0.62658091, "priceChangePercentage7d": 7.33878792}, {"id": 1, "name": "Bitcoin", "slug": "bitcoin", "price": 41739.09712428365, "priceChangePercentage24h": 7.96369773, "priceChangePercentage7d": 24.14504662}, {"id": 3625, "name": "QuadrantProtocol", "slug": "quadrantprotocol", "price": 0.00496945938222, "priceChangePercentage24h": 5.7610273, "priceChangePercentage7d": 21.72897444}, {"id": 2332, "name": "STRAKS", "slug": "straks", "price": 0.0012940856215, "priceChangePercentage24h": 8.04251228, "priceChangePercentage7d": -30.02462566}, {"id": 5712, "name": "FinNexus", "slug": "finnexus", "price": 0.00017488995371, "priceChangePercentage24h": -97.59920819, "priceChangePercentage7d": -97.54470274}, {"id": 6978, "name": "Candela Coin", "slug": "candelacoin", "price": 0.0015775481964, "priceChangePercentage24h": -9.2192815, "priceChangePercentage7d": 12.62534829}, {"id": 7083, "name": "Uniswap", "slug": "uniswap", "price": 21.33512855278244, "priceChangePercentage24h": 8.61733908, "priceChangePercentage7d": 16.45531357}, {"id": 1042, "name": "Siacoin", "slug": "siacoin", "price": 0.01409432366529, "priceChangePercentage24h": 7.34986679, "priceChangePercentage7d": 26.15962794}], "relatedExchanges": [], "isAudited": false, "holders": {}}, "status": {"timestamp": "2021-07-31T08:55:03.014Z", "error_code": "0", "error_message": "SUCCESS", "elapsed": "213", "credit_count": 0}}