{"data": {"id": 4324, "name": "Junsonmingchncoin", "symbol": "JMC", "slug": "junsonmingchncoin", "category": "coin", "description": "Junsonmingchan coin (JMC) describes itself as a digital currency that uses the proof-of-stake consensus algorithm. JMC users have the ability to participate in transaction verification process and get rewarded for it with new JMC coins (proof-of-stake minting).", "dateAdded": "2019-08-30T00:00:00.000Z", "status": "active", "notice": "", "latestUpdateTime": "2021-07-31T08:58:06.000Z", "watchCount": "1323", "launchPrice": 8.39012e-07, "tags": [], "urls": {"website": ["http://jmccoin.com"], "technical_doc": [], "explorer": ["http://jmcblock.com/"], "source_code": ["https://github.com/bastilar/junson-ming-chan-coin"], "message_board": [], "chat": ["https://discord.gg/UW8AJvJ", "https://t.me/jmc_coin_group"], "announcement": ["https://bitcointalk.org/index.php?topic=4882508.0"], "reddit": [], "twitter": ["https://twitter.com/JMC_Coin"]}, "volume": 11.00076835, "volumeChangePercentage24h": 174.3903, "statistics": {"price": 8.3451529e-07, "priceChangePercentage1h": 0.47844467, "priceChangePercentage24h": 115.29532988, "priceChangePercentage7d": 23.99479574, "priceChangePercentage30d": 24.72522722, "priceChangePercentage60d": 15.34824865, "priceChangePercentage90d": -50.7703725, "marketCap": 0.0, "marketCapChangePercentage24h": 0.0, "fullyDilutedMarketCap": 19505.85, "fullyDilutedMarketCapChangePercentage24h": 116.71, "circulatingSupply": 0.0, "totalSupply": 23373872461.0, "marketCapDominance": 0.0, "rank": 5022, "roi": -0.535953, "low24h": 3.8e-07, "high24h": 8.4e-07, "low7d": 3.4e-07, "high7d": 8.4e-07, "low30d": 3e-07, "high30d": 8.4e-07, "low90d": 2.9e-07, "high90d": 1.79e-06, "low52w": 1.7e-07, "high52w": 2.16e-06, "lowAllTime": 1.7e-07, "highAllTime": 2.16e-06, "lowAllTimeChangePercentage": 390.89, "highAllTimeChangePercentage": -61.37, "lowAllTimeTimestamp": "2020-11-28T10:17:03.000Z", "highAllTimeTimestamp": "2021-04-22T03:23:04.000Z", "lowYesterday": 3.8e-07, "highYesterday": 8.3e-07, "openYesterday": 8e-07, "closeYesterday": 4.2e-07, "priceChangePercentageYesterday": -47.5, "volumeYesterday": 11.13, "ytdPriceChangePercentage": 41.4433}, "relatedCoins": [{"id": 1720, "name": "IOTA", "slug": "iota", "price": 0.84939212524204, "priceChangePercentage24h": 4.24144119, "priceChangePercentage7d": 23.20995203}, {"id": 7010, "name": "BNBDOWN", "slug": "bnbdown", "price": 1.15865614283485, "priceChangePercentage24h": -8.49977248, "priceChangePercentage7d": -27.34333095}, {"id": 3456, "name": "PlusOneCoin", "slug": "plusonecoin", "price": 0.00542434939847, "priceChangePercentage24h": 34.55958163, "priceChangePercentage7d": 59.59726168}, {"id": 2469, "name": "Zilliqa", "slug": "zilliqa", "price": 0.07981834335304, "priceChangePercentage24h": 6.58275161, "priceChangePercentage7d": 25.56463476}, {"id": 1732, "name": "Numeraire", "slug": "numeraire", "price": 38.87212615709763, "priceChangePercentage24h": 5.38166745, "priceChangePercentage7d": 19.92122}, {"id": 693, "name": "Verge", "slug": "verge", "price": 0.02291302246854, "priceChangePercentage24h": 8.11247608, "priceChangePercentage7d": 18.37423707}, {"id": 1908, "name": "Nebulas", "slug": "nebulas-token", "price": 0.33721071485075, "priceChangePercentage24h": 3.78986066, "priceChangePercentage7d": 11.67119817}, {"id": 6636, "name": "Polkadot", "slug": "polkadot-new", "price": 16.30329300745868, "priceChangePercentage24h": 10.3919654, "priceChangePercentage7d": 21.64424851}, {"id": 2539, "name": "Ren", "slug": "ren", "price": 0.43706741477533, "priceChangePercentage24h": 18.34064884, "priceChangePercentage7d": 29.14263586}], "relatedExchanges": [], "isAudited": false, "holders": {}}, "status": {"timestamp": "2021-07-31T08:58:58.278Z", "error_code": "0", "error_message": "SUCCESS", "elapsed": "5", "credit_count": 0}}