{"data": {"id": 4819, "name": "DMme", "symbol": "DMME", "slug": "dmme", "category": "token", "description": "## What Is DMme (DMME)?\n\nDMme is a messaging application that uses the [Ethereum blockchain](https://coinmarketcap.com/currencies/ethereum/). \n\nThe main goal for DMme is to allow users to communicate securely, protecting both their identity and data, though \u201cmilitary grade end-to-end encryption.\" \n\nThe project was launched in January 2020 and is available in Google Play. Its iOS version was expected in April 2020, but hadn\u2019t materialized by the end of the year. \n\nThere is little information available about when it might be available, while DMme\u2019s official website does not seem to work.\n\n\n### Who Are the Founders of DMme?\u00ad\n\nThe main name behind DMme is Twitter user CryptoMocho. They are responsible for giving updates on the project \u2014 and their messages are regularly retweeted by DMme\u2019s official account. \n\nThe rest of the team known to the public also uses aliases. Gremlins and Scar69_ are in charge of marketing, Bio_logik is an advisor, Daywalker_ is a developer, while the source code was produced by a private development company.\n\n \n\nCryptoMocho has 129,000 followers on Twitter, but the DMme.app official account has just over 1,000 followers. The official account last posted in August 2020, giving no further updates about the project other than a video showing a \u201cdeveloper update.\u201d In mid-July, a \u201csneak peak\u201d of what the app would look like was released, containing four screenshots.\n\n\n#### What Makes DMme Unique?\n\nDMme is described as a messaging app that uses military encryption technology to protect user information. \n\nWhile files and messages are stored on WhatsApp or Telegram servers, DMme is said to store all data in the user\u2019s phone. To join the app, no phone number has to be shared and only an email address is needed. DMme encourages users to create a new email address when registering.\n\n \n\nSince there has been no [whitepaper](https://coinmarketcap.com/alexandria/glossary/whitepaper) published, and the code is not open source, there is very little information about the technicalities of the project. It is said to use AES-256 encryption, which is the Advanced Encryption Standard with a 256-bit key size.\n\n \n\nDMme is an [ERC-20](https://coinmarketcap.com/alexandria/glossary/erc-20) [token](https://coinmarketcap.com/alexandria/glossary/token) using Ethereum\u2019s blockchain. There are a couple of ERC-20 tokens that provide privacy features such as [Status](https://coinmarketcap.com/currencies/status) and [Orchid](https://coinmarketcap.com/currencies/orchid). \n\nHowever, unlike DMme, these projects are open source and available for audit. Nevertheless, the idea is that the DMme token will be used to pay for subscriptions that allow the team to update the app and develop new features. The project is self-funded and, according to the DMme team, this ensures executives are invested in its success.\n\n\n#### Related Pages:\n\n[Learn more about cryptocurrencies](https://coinmarketcap.com/alexandria).\n\n[Stay up-to-date with the latest crypto headlines](https://coinmarketcap.com/headlines/news/).\n\n[Subscribe to the CoinMarketCap newsletter](https://coinmarketcap.com/newsletter/).\n\n\n#### How Many DMme (DMME) Coins Are There in Circulation?\n\nThere are just over six million coins in circulation, while the team is holding on to 10 million. According to the DMME Token Tracker, there were 270 DMME holders by the end of 2020, while a total of 60 million coins will be issued.\n\n\n### How Is the DMme Network Secured?\n\nThe DMme team is said to be planning to build an ecosystem around the app, which will include a [peer-to-peer](https://coinmarketcap.com/alexandria/glossary/peer-to-peer-p2p) service where DMME would be used as a payment method. It is also said that DMme holders will be paid a monthly dividend for holding DMME [tokens](https://coinmarketcap.com/alexandria/glossary/token).\n\n \n\nThe official DMme.app Twitter account has a pinned tweet dated August 4, 2020, stating that anyone holding 100,000 DMME in their wallet would earn a share of 333,000 DMME on the 10th of each month as long as they hold DMME for a minimum of 20 days.\n\n\n### Where Can You Buy DMme (DMME)?\n\nDMME is available at SatoExchange, Uniswap, Tidex and CREX24. \n\n[Read more here about how to buy Bitcoin.](https://coinmarketcap.com/how-to-buy-bitcoin/)", "dateAdded": "2019-11-06T00:00:00.000Z", "status": "active", "notice": "", "latestUpdateTime": "2021-07-31T09:00:42.000Z", "watchCount": "718", "dateLaunched": "2019-02-25T00:00:00.000Z", "launchPrice": 0.0197349, "tags": [], "urls": {"website": ["https://dmme.app/"], "technical_doc": [], "explorer": ["https://etherscan.io/token/0x9556f8ee795d991ff371f547162d5efb2769425f", "https://ethplorer.io/address/0x9556f8ee795d991ff371f547162d5efb2769425f"], "source_code": [], "message_board": ["https://medium.com/@.Bio_Logik."], "chat": ["https://discordapp.com/invite/AQY6zab", "https://t.me/Dmmecoin"], "announcement": ["https://bitcointalk.org/index.php?topic=5106323.0"], "reddit": [], "twitter": []}, "volume": 6.32047238, "volumeChangePercentage24h": 0.0, "statistics": {"price": 0.00083425540816, "priceChangePercentage1h": 0.39215081, "priceChangePercentage24h": 7.63044431, "priceChangePercentage7d": 65.36667559, "priceChangePercentage30d": -16.95841889, "priceChangePercentage60d": -54.00338262, "priceChangePercentage90d": -87.70235692, "marketCap": 0.0, "marketCapChangePercentage24h": 0.0, "fullyDilutedMarketCap": 13454.94, "fullyDilutedMarketCapChangePercentage24h": 8.35, "circulatingSupply": 0.0, "totalSupply": 16128077.0, "marketCapDominance": 0.0, "rank": 5048, "roi": -95.77481205, "low24h": 0.00076798, "high24h": 0.00084471, "low7d": 0.00036916, "high7d": 0.00301751, "low30d": 0.0002952, "high30d": 0.00301751, "low90d": 0.0002952, "high90d": 0.00714232, "low52w": 0.0002952, "high52w": 0.02827719, "lowAllTime": 0.0002952, "highAllTime": 0.03094796, "lowAllTimeChangePercentage": 182.61, "highAllTimeChangePercentage": -97.3, "lowAllTimeTimestamp": "2021-07-20T22:53:06.000Z", "highAllTimeTimestamp": "2019-11-17T18:46:12.000Z", "lowYesterday": 0.00076798, "highYesterday": 0.00084471, "openYesterday": 0.00080017, "closeYesterday": 0.00084471, "priceChangePercentageYesterday": 5.57, "volumeYesterday": 6.4, "ytdPriceChangePercentage": -71.527}, "platforms": [{"contractId": 1027, "contractAddress": "0x9556f8ee795d991ff371f547162d5efb2769425f", "contractPlatform": "Ethereum", "contractPlatformId": 1, "contractChainId": 1, "contractRpcUrl": ["https://bsc-dataseed1.binance.org", "https://bsc-dataseed.binance.org/", "https://bsc-dataseed1.binance.org:443"], "contractNativeCurrencyName": "Ethereum", "contractNativeCurrencySymbol": "ETH", "contractNativeCurrencyDecimals": 18, "contractBlockExplorerUrl": "https://etherscan.io", "contractExplorerUrl": "https://etherscan.io/token/0x9556f8ee795d991ff371f547162d5efb2769425f", "contractDecimals": 18, "platformCryptoId": 1027}], "relatedCoins": [{"id": 2001, "name": "ColossusXT", "slug": "colossusxt", "price": 0.00021502475916, "priceChangePercentage24h": 82.79897024, "priceChangePercentage7d": 104.95830478}, {"id": 1817, "name": "Voyager Token", "slug": "voyager-token", "price": 2.41361322951641, "priceChangePercentage24h": 20.52711448, "priceChangePercentage7d": 30.09344518}, {"id": 2549, "name": "Ink Protocol", "slug": "ink-protocol", "price": 0.00154642363149, "priceChangePercentage24h": 6.50877516, "priceChangePercentage7d": 17.19078319}, {"id": 6839, "name": "KIMCHI.finance", "slug": "kimchi-finance", "price": 0.00027746396192, "priceChangePercentage24h": 8.64780919, "priceChangePercentage7d": 4.82117081}, {"id": 2717, "name": "BoutsPro", "slug": "boutspro", "price": 0.00418835593524, "priceChangePercentage24h": 3.98229596, "priceChangePercentage7d": -49.4391018}, {"id": 7609, "name": "Fiola", "slug": "fiola", "price": 0.0001115656689, "priceChangePercentage24h": 2.5254712, "priceChangePercentage7d": 8.18185883}, {"id": 7323, "name": "XCredit", "slug": "xcredit", "price": 4.92186494881597, "priceChangePercentage24h": 4.70669457, "priceChangePercentage7d": 1814.92001024}, {"id": 2713, "name": "KEY", "slug": "key", "price": 0.00051522223858, "priceChangePercentage24h": 0.00335736, "priceChangePercentage7d": 3.41049844}, {"id": 2056, "name": "PiplCoin", "slug": "piplcoin", "price": 0.00083383661713, "priceChangePercentage24h": 7.66729641, "priceChangePercentage7d": -17.40720196}], "relatedExchanges": [{"id": 219, "name": "Tidex", "slug": "tidex"}, {"id": 382, "name": "Crex24", "slug": "crex24"}], "wallets": [{"id": 9022, "name": "Trust Wallet", "tier": 1, "url": "https://www.trustwallet.com/", "chains": "ETH", "types": "app,trade", "introduction": "", "star": 2.0, "security": 3.0, "easyToUse": 3.0, "decentration": true, "focusNumber": 0, "rank": 1000008, "logo": "9022.png", "multipleChain": true}, {"id": 9025, "name": "MetaMask", "tier": 1, "url": "https://metamask.io/", "chains": "ETH,ETZ", "types": "pc", "introduction": "", "star": 1.0, "security": 2.0, "easyToUse": 4.0, "decentration": false, "focusNumber": 0, "rank": 1000013, "logo": "9025.png", "multipleChain": true}], "isAudited": false, "holders": {"holderCount": 289, "holderList": [{"address": "0x000000000000000000000000000000000000dead", "balance": 43891923, "share": 73.15}, {"address": "0x782db3ae31a7406849c84f9bb0189defdd26b4d2", "balance": 3002306.0111872195, "share": 5}, {"address": "0xaa433f5d9d0911bfb7a3d6d9ba2880a23bdf4c31", "balance": 1031645.5160396761, "share": 1.72}, {"address": "0x521db06bf657ed1d6c98553a70319a8ddbac75a3", "balance": 968200.1308788703, "share": 1.61}, {"address": "0x7f5e650275c8e0dee8e571c28542226d1bef36ce", "balance": 833677.8121835295, "share": 1.39}, {"address": "0x3083dbe662596bc0d8bfebf2d88c3fed827011ab", "balance": 700000.0, "share": 1.17}, {"address": "0xf63d2a8c6990d5bd176ec03b3bad192b3f0a456a", "balance": 375000.0, "share": 0.63}, {"address": "0x2be60debf912741747e5eba2f077947cea3fd2da", "balance": 365293.39139212336, "share": 0.61}, {"address": "0xf010d53cba1c1dd9b73b910a547b4a833dd3908b", "balance": 351805, "share": 0.59}, {"address": "0x984f2e483f80d7fb7a94fff3dfb118607f84adde", "balance": 315456.31706059, "share": 0.53}, {"address": "0x9b6feae60cfbc17323732489bdbe438bbb033d40", "balance": 313228.8551327881, "share": 0.52}, {"address": "0x723c0dcb6475da8e06b7bd11980cbe058d86d209", "balance": 310000.0, "share": 0.52}, {"address": "0xbb25d403ba3e3ee7fce1fe1a07714ebc586935e7", "balance": 306735.0876447, "share": 0.51}, {"address": "0x9e60cc2beabcb738621e448ea92617a4acb73104", "balance": 300000.0, "share": 0.5}, {"address": "0x2cce4364571c6ab6114aa43594507d03614d39b4", "balance": 290000.0, "share": 0.48}, {"address": "0x06424e4c7d02ff927e4fa4f3fedad77581b265a3", "balance": 282528.48204737, "share": 0.47}, {"address": "0x2d2c84c36326254be6356c8ed521e22269f8b29a", "balance": 257991, "share": 0.43}, {"address": "0xbeaafc5e2d22fa1b7fcf3e01520ede14aef934b5", "balance": 213650.103, "share": 0.36}, {"address": "0x4587ed5a0a0474bc4a5de4ab3a8ee4a58b8a3a3a", "balance": 209047.31057045, "share": 0.35}, {"address": "0xdd1e333f42dc4f1e458f8a46d9d81eaebc182ba2", "balance": 200007, "share": 0.33}, {"address": "0x656868a2ae03aa1e3ec656eabade249e74eecb83", "balance": 187142, "share": 0.31}, {"address": "0x892f6c794fe9c3fcaa546600c3f0b688b30df5f3", "balance": 166295.59574462, "share": 0.28}, {"address": "0xe700535e4d9d666d64ab698000c947fc30597f86", "balance": 156754.46678218, "share": 0.26}, {"address": "0xe3214142347338f1f65adf502feb2f125330b7ee", "balance": 153187.60572135, "share": 0.26}, {"address": "0x5565e90b36d019d3e116cf66288ef5696a48f36c", "balance": 139907, "share": 0.23}, {"address": "0x9c5e4487678af2b777682f4a17fc223ee8aada77", "balance": 138707, "share": 0.23}, {"address": "0xa5235a803bbc0abc5544d6677b3ee098f85716a2", "balance": 136795.72550281, "share": 0.23}, {"address": "0xe58094e78c5bc98b1bd411f5d6931593ae52965d", "balance": 133594.26250095, "share": 0.22}, {"address": "0x8f6ecd7f785f8431770d097d7f809480464fc3d3", "balance": 132365.99296631, "share": 0.22}, {"address": "0x98fdb61d8dd16313ad036b18c675029bb1e22f6f", "balance": 131263, "share": 0.22}, {"address": "0x53dfdd80909e8af7a8d9a1f950965c8121a585e9", "balance": 131166.648359424, "share": 0.22}, {"address": "0xe73d4620a7c9f77ebd623a1b82631e359b2b4674", "balance": 130335.54840785, "share": 0.22}, {"address": "0x442747e725d0e1d1fe46c3635f8e01253b6d1ec7", "balance": 130131.7883358701, "share": 0.22}, {"address": "0x176f6881a16daece41b28de8fb9d19208f655c80", "balance": 129926.31562188, "share": 0.22}, {"address": "0x83f81720e2cef8e246a3c24db897afeb48a978fa", "balance": 129912.70021633, "share": 0.22}, {"address": "0xa6aa89c24428476556ec6cca1ff41000ac8a1089", "balance": 129797.42751011, "share": 0.22}, {"address": "0x5722e92b83a66a47db6275415df0f7f10e56a1fb", "balance": 129712, "share": 0.22}, {"address": "0x39caa5e5109934b63f338f14d93d13ee1b005e10", "balance": 120590.9314, "share": 0.2}, {"address": "0x83b6bd03dae3b46248dfb6a2aac87ed80be46eb9", "balance": 120000.0, "share": 0.2}, {"address": "0xb75994a4972e07e2a37b89d716685aecbba6c0c4", "balance": 100000.0, "share": 0.17}, {"address": "0x91cca775d0c16230bfa532e89876808b1229c176", "balance": 97000.0, "share": 0.16}, {"address": "0x2cfd25f7c59c5f99bfe2c85399103600a6a6f548", "balance": 94889.69237745558, "share": 0.16}, {"address": "0x30d3def4d470a6680fd2805cf0ddf2c7cf671174", "balance": 93617, "share": 0.16}, {"address": "0xc1534b3b2bb29d076c4f9f6ab753f155aa30b9ca", "balance": 82073.5, "share": 0.14}, {"address": "0xfa676ab0be3b0a88a2be7edb97798f6403cdbcc1", "balance": 74282.0952, "share": 0.12}, {"address": "0x0a6f2a654a8e38600b9a4da506a1dc31583fa516", "balance": 71199.75701688, "share": 0.12}, {"address": "0xb92a89643eb3e04938746c1e2b68228865fa46e3", "balance": 69130.33820588, "share": 0.12}, {"address": "0xaef0c9e05c14750cd5c7d87b81b59ccc4ef5aadb", "balance": 68574.60561174454, "share": 0.11}, {"address": "0x0609dda7f8bf3ad59241b6a320c67c94c2afc1ef", "balance": 64450.0, "share": 0.11}, {"address": "0xcdc52494fbcfbe85a636cb4b849c4b41aeaba282", "balance": 63705.74204491025, "share": 0.11}, {"address": "0xf1c37a01b0f32e3a617655ac458127a336747176", "balance": 62941.52594641, "share": 0.1}, {"address": "0x0270e088aa5ca71cf3b3c5d2edeae01a871da3d3", "balance": 57305, "share": 0.1}, {"address": "0x237557330758634b6c28d12d75799216f9309470", "balance": 55911.39809932837, "share": 0.09}, {"address": "0xda3cc1220fd5213a0b98efa60b43dfa2a1a18188", "balance": 55743.86197358, "share": 0.09}, {"address": "0xc12f0f9e2d81d3849662c8360827a7818d1ee875", "balance": 53233.27167209, "share": 0.09}, {"address": "0xadd457c9cd426b68fe2929366531f6861d299396", "balance": 52557.20990148124, "share": 0.09}, {"address": "0x4c23769bbbe0127156e1d2ce67f797b69fe73263", "balance": 50100.0, "share": 0.08}, {"address": "0xaed604eebddd82b8b580d5855d44c4e868304bc5", "balance": 50000.0, "share": 0.08}, {"address": "0xbc4f507f48b930cdf2c21f8894e5d94b342679b0", "balance": 49102, "share": 0.08}, {"address": "0xdd6f02785213d230634243cf3e26b01c9be4d515", "balance": 43118.5258182, "share": 0.07}, {"address": "0x603b6aece43794b4743371194b9578aa2767824a", "balance": 42511.4, "share": 0.07}, {"address": "0x1ffb8f948777a3f3701f72184bb9b9ddc6312bc6", "balance": 41344.01641934366, "share": 0.07}, {"address": "0x66c76d44f3e7c9102c20c6338098684075a45167", "balance": 40400.0, "share": 0.07}, {"address": "0xb2d3df731ffa6d9d29225ccc76641b4064cf131c", "balance": 38397.4975, "share": 0.06}, {"address": "0x1d9491ed7723df530378d322b3f7075ec8b7a91c", "balance": 36922.2263296, "share": 0.06}, {"address": "0x6de8e6515ae5153aab62ee89cfc3a8237df4dbbc", "balance": 36559.61538461, "share": 0.06}, {"address": "0x3a80976317b0dc93ce466e26d7b5374d23573b31", "balance": 35020.76652341, "share": 0.06}, {"address": "0x4b3151c95300778c97d1da2b156db99f7d73a875", "balance": 34590.5, "share": 0.06}, {"address": "0x16cde6b2834e40075b44a22d1dd64b89aedccc00", "balance": 34364.795, "share": 0.06}, {"address": "0xc97d990b257a6c48fde803eab98b6720e76acaab", "balance": 32253.923295485827, "share": 0.05}, {"address": "0xac3b79291777d84c77f2649f314fad65be173d97", "balance": 32043.457020225505, "share": 0.05}, {"address": "0x5a661bdab1c6f2bbdda0ba7282047ff1cc324422", "balance": 31615.620028851055, "share": 0.05}, {"address": "0x66a4e99923ff534c41936d0b28a13980b0a942f0", "balance": 27137.850371289464, "share": 0.05}, {"address": "0x1ac376d14047c639cf6efeca10ad1d1a86c60880", "balance": 26648, "share": 0.04}, {"address": "0x444c5689c26e0aef18a15d9b3490d2160742699c", "balance": 26008.49633707, "share": 0.04}, {"address": "0x71e10deec82714f372eabbb2288ba5610d7ec108", "balance": 25983.46999134, "share": 0.04}, {"address": "0x88bc01983558478bddaee406732df9a1d484eed9", "balance": 24541.86008991, "share": 0.04}, {"address": "0xe38068b2018c83f201cdbb87a5746e3e1fe9fe1e", "balance": 24089.0028, "share": 0.04}, {"address": "0xae19a728689dd067d404b58863f932719180c08f", "balance": 22926.662208185884, "share": 0.04}, {"address": "0xccda9bd29a0c8a65b2c909791e10302079120a6e", "balance": 22901.759494169695, "share": 0.04}, {"address": "0x92d648329cb42f5ef167817d76d81621fe84c271", "balance": 22500.0, "share": 0.04}, {"address": "0x72b0c137b3253f9758164e69adbcb8ad114f8af4", "balance": 22326.14275879405, "share": 0.04}, {"address": "0x07ca3a4c0c69aa01bac48184132d081273c0b90e", "balance": 21343.555, "share": 0.04}, {"address": "0xf6e8b99c0676afd935ec2831aacf01befbe69160", "balance": 20469.9599, "share": 0.03}, {"address": "0x4bff2e960687f170ce4a47d19d71ae9139bf063b", "balance": 20252.74725275, "share": 0.03}, {"address": "0xb37607a34825d573945f43b4552ba60b1fbfec6a", "balance": 20100.0, "share": 0.03}, {"address": "0x0015cc326c29459d5236b9167740c2214a300439", "balance": 19858, "share": 0.03}, {"address": "0x3795b99806683036a4790c8f36b641ce6438141e", "balance": 19584.379, "share": 0.03}, {"address": "0xa3645147f051c1c1c0deedf38a725b50a33dd4a9", "balance": 19148.47532978601, "share": 0.03}, {"address": "0x40294e432ebb5929c039e9a19404e6ab1a78486d", "balance": 17979.0646, "share": 0.03}, {"address": "0x3437977299514fa6a7cc227ba9a2cfbc84db1ebe", "balance": 17979.0646, "share": 0.03}, {"address": "0x3009de2241da7fc24bf3a7b5c454e4e6f20fc373", "balance": 16648.011988, "share": 0.03}, {"address": "0x85d38002d669a371b36d72666b8e36b2bd2758d8", "balance": 15769.27914, "share": 0.03}, {"address": "0xf28fcf7d84747bb661a85bb8047769c8b4d178c0", "balance": 15213, "share": 0.03}, {"address": "0x4dd200f24ebb35624c04b101dbfeb4584d350e9b", "balance": 15023.24435, "share": 0.03}, {"address": "0xc77916c6fc00ba9b9441a205a8de4c435259e45b", "balance": 14694.92955221, "share": 0.02}, {"address": "0x79f371037495b4d59f5560037f7b0c2cc48e1302", "balance": 14252.445719730935, "share": 0.02}, {"address": "0x2ce420b0ce670d55feec71be2cc37cfd217f70a2", "balance": 14163, "share": 0.02}, {"address": "0xde98e037017f9d2e63f933611f9987cf005e6bc8", "balance": 13994.2795, "share": 0.02}, {"address": "0xe3785df635fadba91fbc20fdf790964096c9d64a", "balance": 13672.16476091, "share": 0.02}], "topTenHolderRatio": 86.4, "topTwentyHolderRatio": 90.87, "topFiftyHolderRatio": 96.75, "topHundredHolderRatio": 99.25}}, "status": {"timestamp": "2021-07-31T09:02:21.980Z", "error_code": "0", "error_message": "SUCCESS", "elapsed": "6", "credit_count": 0}}