{"data": {"id": 8177, "name": "KnoxFS (new)", "symbol": "KFX", "slug": "knoxfs-new", "category": "coin", "description": "KnoxFS (new) (KFX) is a cryptocurrency . KnoxFS (new) has a current supply of 422,094.45347256. The last known price of KnoxFS (new) is 0.43335047 USD and is up 7.27 over the last 24 hours. It is currently trading on 4 active market(s) with $13,019.56 traded over the last 24 hours. More information can be found at https://www.knoxfs.com/.", "dateAdded": "2021-01-05T00:00:00.000Z", "status": "active", "notice": "", "latestUpdateTime": "2021-07-31T09:24:40.000Z", "watchCount": "242", "tags": [{"slug": "storage", "name": "Storage", "category": "PROPERTY"}], "selfReportedTags": ["Software", "Staking", "Storage", "Masternodes", "Services", "Filesharing", "PIVX", "PoS"], "selfReportedCirculatingSupply": "412008.95607922", "urls": {"website": ["https://www.knoxfs.com/"], "technical_doc": [], "explorer": ["https://explorer.knoxfs.com/"], "source_code": [], "message_board": [], "chat": ["https://t.me/knoxFSOfficial", "https://discord.gg/bTtgmMf"], "announcement": [], "reddit": [], "twitter": ["https://twitter.com/OKnoxfs"]}, "volume": 12988.29183912, "volumeChangePercentage24h": 61.1506, "statistics": {"price": 0.4328936835969, "priceChangePercentage1h": -1.26042934, "priceChangePercentage24h": 7.18415695, "priceChangePercentage7d": -5.38984314, "priceChangePercentage30d": 6.67773845, "priceChangePercentage60d": -14.90615367, "priceChangePercentage90d": -74.90765572, "marketCap": 182722.02, "marketCapChangePercentage24h": 7.2682, "fullyDilutedMarketCap": 182722.02, "fullyDilutedMarketCapChangePercentage24h": -14.15, "circulatingSupply": 422094.45347256, "totalSupply": 422094.45347256, "marketCapDominance": 0.0, "rank": 2089, "low24h": 0.39730671, "high24h": 0.53218429, "low7d": 0.3842108, "high7d": 0.53218429, "low30d": 0.37907551, "high30d": 0.53218429, "low90d": 0.34170413, "high90d": 2.96019924, "low52w": 0.07047753, "high52w": 4.58478538, "lowAllTime": 0.07047753, "highAllTime": 4.58478538, "lowAllTimeChangePercentage": 514.23, "highAllTimeChangePercentage": -90.56, "lowAllTimeTimestamp": "2021-01-30T06:17:08.000Z", "highAllTimeTimestamp": "2021-01-17T21:33:11.000Z", "lowYesterday": 0.39730671, "highYesterday": 0.53218429, "openYesterday": 0.40194709, "closeYesterday": 0.42543328, "priceChangePercentageYesterday": 5.84, "volumeYesterday": 14303.66, "turnover": 0.07108225, "ytdPriceChangePercentage": 0.0}, "relatedCoins": [{"id": 1299, "name": "PutinCoin", "slug": "putincoin", "price": 0.00050051041644, "priceChangePercentage24h": -0.20920187, "priceChangePercentage7d": -0.87322045}, {"id": 7278, "name": "Aave", "slug": "aave", "price": 319.2474369719818, "priceChangePercentage24h": 5.5066996, "priceChangePercentage7d": 9.64109521}, {"id": 2496, "name": "Polymath", "slug": "polymath-network", "price": 0.2663297076882, "priceChangePercentage24h": 3.64779829, "priceChangePercentage7d": 39.0181357}, {"id": 7376, "name": "Doki Doki Finance", "slug": "doki-doki-finance", "price": 42.94562377495086, "priceChangePercentage24h": 0.62053268, "priceChangePercentage7d": 20.04771234}, {"id": 2416, "name": "THETA", "slug": "theta", "price": 5.98003746480648, "priceChangePercentage24h": 4.50653921, "priceChangePercentage7d": 9.24491096}, {"id": 5355, "name": "Chainpay", "slug": "chainpay", "price": 0.75696886569524, "priceChangePercentage24h": 46.72477767, "priceChangePercentage7d": 1419.934349}, {"id": 7805, "name": "Muse", "slug": "muse", "price": 32.17043262850505, "priceChangePercentage24h": 48.89001793, "priceChangePercentage7d": 34.5953844}, {"id": 6538, "name": "Curve DAO Token", "slug": "curve-dao-token", "price": 1.71762976374205, "priceChangePercentage24h": 11.78644019, "priceChangePercentage7d": 10.5525873}, {"id": 6187, "name": "Serum", "slug": "serum", "price": 3.90366583407328, "priceChangePercentage24h": 13.68264547, "priceChangePercentage7d": 35.2662592}, {"id": 1982, "name": "Kyber Network Crystal Legacy", "slug": "kyber-network-crystal-legacy", "price": 1.60813767018895, "priceChangePercentage24h": 13.60314947, "priceChangePercentage7d": 18.40663878}], "relatedExchanges": [{"id": 215, "name": "P2PB2B", "slug": "p2pb2b"}, {"id": 154, "name": "Dex-Trade", "slug": "dex-trade"}, {"id": 382, "name": "Crex24", "slug": "crex24"}], "isAudited": false, "holders": {}}, "status": {"timestamp": "2021-07-31T09:25:51.504Z", "error_code": "0", "error_message": "SUCCESS", "elapsed": "8", "credit_count": 0}}