{"data": {"id": 8734, "name": "CheapETH", "symbol": "CTH", "slug": "cheapeth", "category": "coin", "description": "The transaction fees on Ethereum do not scale with the amount of money moved, where if there was a way to apply different amounts of security to them, they should.\r\n\r\nThat's where cheapETH comes in. It's just as capable of doing all the same compute and contract operations, but it's not capable of securing all the value. It's a home for fast in and out high value, lower value, or no value transactions. We estimate 99% of the Ethereum transactions require nowhere near the security of the entire Ethereum blockchain, yet they all pay for it and get it every time. cheapETH lets you not pay for it if you don't need it.", "dateAdded": "2021-03-09T00:00:00.000Z", "status": "untracked", "notice": "", "latestUpdateTime": "", "watchCount": "60", "dateLaunched": "2021-02-03T00:00:00.000Z", "tags": [], "urls": {"website": ["https://cheapeth.org/"], "technical_doc": [], "explorer": ["https://expedition.dev/?rpcUrl=https://node.cheapeth.org/rpc", "https://explore.cheapswap.io/"], "source_code": [], "message_board": ["https://discord.gg/r3WUGxzUH8"], "chat": [], "announcement": [], "reddit": [], "twitter": []}, "relatedCoins": [{"id": 1376, "name": "Neo", "slug": "neo", "price": 47.10354213653963, "priceChangePercentage24h": 39.65194998, "priceChangePercentage7d": 55.06568904}, {"id": 6636, "name": "Polkadot", "slug": "polkadot-new", "price": 16.20921272842714, "priceChangePercentage24h": 11.38890528, "priceChangePercentage7d": 21.01884371}, {"id": 109, "name": "DigiByte", "slug": "digibyte", "price": 0.04645557032689, "priceChangePercentage24h": 9.52906873, "priceChangePercentage7d": 20.09673529}, {"id": 1817, "name": "Voyager Token", "slug": "voyager-token", "price": 2.33931138166303, "priceChangePercentage24h": 18.16858519, "priceChangePercentage7d": 25.79823054}, {"id": 3077, "name": "VeChain", "slug": "vechain", "price": 0.08930326229174, "priceChangePercentage24h": 11.12865104, "priceChangePercentage7d": 25.30358911}, {"id": 1567, "name": "Nano", "slug": "nano", "price": 4.34455836345464, "priceChangePercentage24h": 5.68352093, "priceChangePercentage7d": 11.08919521}, {"id": 7226, "name": "Injective Protocol", "slug": "injective-protocol", "price": 6.58630853378085, "priceChangePercentage24h": 9.7930536, "priceChangePercentage7d": 13.14130451}, {"id": 2062, "name": "Aion", "slug": "aion", "price": 0.12843118465834, "priceChangePercentage24h": 8.0847086, "priceChangePercentage7d": 13.21234214}, {"id": 3890, "name": "Polygon", "slug": "polygon", "price": 1.05033196197757, "priceChangePercentage24h": 5.1273618, "priceChangePercentage7d": 13.77452442}], "relatedExchanges": [], "isAudited": false}, "status": {"timestamp": "2021-07-31T09:29:49.700Z", "error_code": "0", "error_message": "SUCCESS", "elapsed": "7", "credit_count": 0}}